HCSR04_python_lib/HCSR04.py
HCSR04_python_lib/__init__.py
HCSR04_python_lib-0.0.1.dist-info/LICENSE.txt
HCSR04_python_lib-0.0.1.dist-info/METADATA
HCSR04_python_lib-0.0.1.dist-info/WHEEL
HCSR04_python_lib-0.0.1.dist-info/top_level.txt
HCSR04_python_lib-0.0.1.dist-info/RECORD
