Metadata-Version: 2.1
Name: HCSR04-python-lib
Version: 0.0.1
Summary: Library for HC-SR04 ultrasonic distance sensor used with Raspberry Pi.
Home-page: https://github.com/JakubPrz/HCSR04_python_lib
Download-URL: https://github.com/JakubPrz/HCSR04_python_lib/archive/v0.0.1.tar.gz
Author: Jakub Przepiórka
Author-email: jakub.przepiorka.contact.me@gmail.com
License: MIT
Platform: Linux
Classifier: Development Status :: 3 - Alpha
Classifier: Intended Audience :: Education
Classifier: Intended Audience :: Developers
Classifier: Operating System :: POSIX :: Linux
Classifier: Programming Language :: Python :: 3
Classifier: Programming Language :: Python :: 3.9
Classifier: License :: OSI Approved :: MIT License
Classifier: Topic :: Software Development :: Libraries :: Python Modules
Requires-Python: >=3.9
License-File: LICENSE.txt
Requires-Dist: RPi.GPIO
